kedantic/__init__.py
kedantic/plugin.py
kedantic-0.1.1.dist-info/licenses/LICENSE
test_kedantic/__init__.py
test_kedantic/test_plugin.py
kedantic-0.1.1.dist-info/METADATA
kedantic-0.1.1.dist-info/WHEEL
kedantic-0.1.1.dist-info/entry_points.txt
kedantic-0.1.1.dist-info/top_level.txt
kedantic-0.1.1.dist-info/RECORD
