Metadata-Version: 2.4
Name: kedantic
Version: 0.1.1
Summary: Plugin to allow Pydantic Models as Node Inputs in Kedro
Requires-Python: >=3.10
License-File: LICENSE
Requires-Dist: kedro>=1.1.1
Requires-Dist: pydantic>=2.12.5
Dynamic: license-file
